LICENCE
MANIFEST.in
README.md
pyproject.toml
setup.py
django_rest_spreadsheets.egg-info/PKG-INFO
django_rest_spreadsheets.egg-info/SOURCES.txt
django_rest_spreadsheets.egg-info/dependency_links.txt
django_rest_spreadsheets.egg-info/top_level.txt
spreadsheet/__init__.py
spreadsheet/fields.py
spreadsheet/schema.py
spreadsheet/serializers.py
spreadsheet/urls.py
spreadsheet/util.py
spreadsheet/views.py
spreadsheet/migrations/__init__.py
spreadsheet/static/deps/jquery-ui.css
spreadsheet/static/deps/jquery-ui.js
spreadsheet/static/deps/jquery.datetimepicker.css
spreadsheet/static/deps/jquery.datetimepicker.full.js
spreadsheet/static/deps/jquery.datetimepicker.js
spreadsheet/static/deps/jquery.datetimepicker.min.css
spreadsheet/static/deps/moment.js
spreadsheet/static/spreadsheet/css/menu.css
spreadsheet/static/spreadsheet/css/reset.css
spreadsheet/static/spreadsheet/css/screen.css
spreadsheet/static/spreadsheet/css/spreadsheet.css
spreadsheet/static/spreadsheet/img/cancel.svg
spreadsheet/static/spreadsheet/img/create.svg
spreadsheet/static/spreadsheet/img/delete.svg
spreadsheet/static/spreadsheet/img/icon.png
spreadsheet/static/spreadsheet/img/update.svg
spreadsheet/static/spreadsheet/js/RestApi6.js
spreadsheet/static/spreadsheet/js/ScreenStack.js
spreadsheet/static/spreadsheet/js/SpreadSheet.js
spreadsheet/static/spreadsheet/js/menu.js
spreadsheet/templates/index.html