Metadata-Version: 2.4
Name: django-rest-spreadsheets
Version: 1.0.0
Summary: Spreadsheets based on django rest framework
Home-page: https://github.com/g3rb3n/django-rest-spreadsheets/
Author: gerben van Eerten
Author-email: Gerben van Eerten <info@gerbenvaneerten.nl>
License-Expression: MIT
Project-URL: Homepage, https://github.com/g3rb3n/django-rest-spreadsheets
Project-URL: Issues, https://github.com/g3rb3n/django-rest-spreadsheets/issues
Classifier: Programming Language :: Python :: 3
Classifier: Operating System :: OS Independent
Requires-Python: >=3.9
License-File: LICENCE
Dynamic: author
Dynamic: home-page
Dynamic: license-file
